{"crs": {"properties": {"name": "urn:ogc:def:crs:OGC:1.3:CRS84"}, "type": "name"}, "features": [{"geometry": {"coordinates": [[[41.0863086, 36.1432693], [41.0846819, 36.1411004], [41.0857663, 36.1373048], [41.0901042, 36.1367626], [41.0906464, 36.1411004], [41.0895619, 36.1416427], [41.0890197, 36.1432693], [41.0863086, 36.1432693]]], "type": "Polygon"}, "properties": {"Concentration Uncertainty (ppm m)": 498.0, "DAAC Scene Numbers": ["049"], "DCID": "1364164771", "Latitude of max concentration": 36.13974483722933, "Longitude of max concentration": 41.08712190364524, "Max Plume Concentration (ppm m)": 2315.0, "Orbit": "2309406", "Plume ID": "CH4_PlumeComplex-802", "Scene FIDs": ["emit20230404t090042"], "UTC Time Observed": "2023-04-04T08:58:44Z", "map_endtime": "2023-04-04T08:58:45Z", "DAAC Scene Names": ["EMIT_L2B_CH4ENH_V001_20230404T090042_2309406_049"]}, "type": "Feature"}], "name": "methane_metadata", "type": "FeatureCollection", "center_coords": [41.0877997, 36.140964849999996]}