{"crs": {"properties": {"name": "urn:ogc:def:crs:OGC:1.3:CRS84"}, "type": "name"}, "features": [{"geometry": {"coordinates": [[[34.7454415, 31.3249912], [34.7421881, 31.3217378], [34.7421881, 31.3201111], [34.7448992, 31.3173999], [34.7459837, 31.3173999], [34.7476104, 31.315231], [34.7497793, 31.3146888], [34.7562861, 31.315231], [34.7568283, 31.3190266], [34.7541172, 31.3244489], [34.7454415, 31.3249912]]], "type": "Polygon"}, "properties": {"Concentration Uncertainty (ppm m)": 341.0, "DAAC Scene Numbers": ["039"], "DCID": "1379181456", "Latitude of max concentration": 31.323635592312264, "Longitude of max concentration": 34.74571257924703, "Max Plume Concentration (ppm m)": 1944.0, "Orbit": "2326908", "Plume ID": "CH4_PlumeComplex-1752", "Scene FIDs": ["emit20230926t114119"], "UTC Time Observed": "2023-09-26T11:35:59Z", "map_endtime": "2023-09-26T11:36:00Z", "DAAC Scene Names": ["EMIT_L2B_CH4ENH_V001_20230926T114119_2326908_039"]}, "type": "Feature"}], "name": "methane_metadata", "type": "FeatureCollection", "center_coords": [34.74825121818182, 31.319568854545455]}